bitmart/__init__.py
bitmart/ccxt/__init__.py
bitmart/ccxt/bitmart.py
bitmart/ccxt/abstract/bitmart.py
bitmart/ccxt/async_support/__init__.py
bitmart/ccxt/async_support/bitmart.py
bitmart/ccxt/async_support/base/__init__.py
bitmart/ccxt/async_support/base/exchange.py
bitmart/ccxt/async_support/base/throttler.py
bitmart/ccxt/async_support/base/ws/__init__.py
bitmart/ccxt/async_support/base/ws/cache.py
bitmart/ccxt/async_support/base/ws/client.py
bitmart/ccxt/async_support/base/ws/functions.py
bitmart/ccxt/async_support/base/ws/future.py
bitmart/ccxt/async_support/base/ws/order_book.py
bitmart/ccxt/async_support/base/ws/order_book_side.py
bitmart/ccxt/base/__init__.py
bitmart/ccxt/base/decimal_to_precision.py
bitmart/ccxt/base/errors.py
bitmart/ccxt/base/exchange.py
bitmart/ccxt/base/precise.py
bitmart/ccxt/base/types.py
bitmart/ccxt/pro/__init__.py
bitmart/ccxt/pro/bitmart.py
bitmart/ccxt/static_dependencies/README.md
bitmart/ccxt/static_dependencies/__init__.py
bitmart/ccxt/static_dependencies/bip/__init__.py
bitmart/ccxt/static_dependencies/bip/addr/P2PKH_addr.py
bitmart/ccxt/static_dependencies/bip/addr/__init__.py
bitmart/ccxt/static_dependencies/bip/addr/addr_dec_utils.py
bitmart/ccxt/static_dependencies/bip/addr/addr_key_validator.py
bitmart/ccxt/static_dependencies/bip/addr/iaddr_decoder.py
bitmart/ccxt/static_dependencies/bip/addr/iaddr_encoder.py
bitmart/ccxt/static_dependencies/bip/base58/__init__.py
bitmart/ccxt/static_dependencies/bip/base58/base58.py
bitmart/ccxt/static_dependencies/bip/base58/base58_ex.py
bitmart/ccxt/static_dependencies/bip/base58/base58_xmr.py
bitmart/ccxt/static_dependencies/bip/bech32/__init__.py
bitmart/ccxt/static_dependencies/bip/bech32/bch_bech32.py
bitmart/ccxt/static_dependencies/bip/bech32/bech32.py
bitmart/ccxt/static_dependencies/bip/bech32/bech32_base.py
bitmart/ccxt/static_dependencies/bip/bech32/bech32_ex.py
bitmart/ccxt/static_dependencies/bip/bech32/segwit_bech32.py
bitmart-0.0.121.dist-info/METADATA
bitmart-0.0.121.dist-info/WHEEL
bitmart-0.0.121.dist-info/RECORD
